testbed/_cors.py
testbed/__init__.py
testbed/tests/redirect.py
testbed/tests/auth.py
testbed/tests/performance.py
testbed/tests/general.py
testbed/tests/exc.py
testbed/tests/datetime_.py
testbed/tests/__init__.py
testbed/tests/echo/_core.py
testbed/tests/echo/__main__.py
testbed/tests/echo/_method.py
testbed/tests/echo/_resource.py
testbed/tests/echo/__init__.py
testbed/scripts/testbed_serve.py
testbed/scripts/__init__.py
testbed/_services/_web.py
testbed/_services/__init__.py
testbed/resources/_exc.py
testbed/resources/_performance.py
testbed/resources/_general.py
testbed/resources/_redirect.py
testbed/resources/_auth.py
testbed/resources/_datetime.py
testbed/resources/__init__.py
testbed/resources/_echo/_method.py
testbed/resources/_echo/_resource.py
testbed/resources/_echo/__init__.py
testbed/testing/_auth.py
testbed/testing/_core.py
testbed/testing/_cors.py
testbed/testing/__init__.py
Testbed-0.13.4.dist-info/top_level.txt
Testbed-0.13.4.dist-info/RECORD
Testbed-0.13.4.dist-info/pydist.json
Testbed-0.13.4.dist-info/WHEEL
Testbed-0.13.4.dist-info/namespace_packages.txt
Testbed-0.13.4.dist-info/METADATA
Testbed-0.13.4.dist-info/entry_points.txt
Testbed-0.13.4.dist-info/DESCRIPTION.rst
Testbed-0.13.4.data/scripts/testbed-serve
