Metadata-Version: 2.0
Name: Testbed
Version: 0.13.4
Summary: A web service that tests Bedframe
Home-page: UNKNOWN
Author: Ivan D Vasin
Author-email: nisavid@gmail.com
License: GNU LESSER GENERAL PUBLIC LICENSE
Requires-Dist: bedframe[test_ldap,tornado_wsgi] (>=0.13.4.dev)
Requires-Dist: pytz
Requires-Dist: requests
Requires-Dist: spruce-collections
Requires-Dist: spruce-datetime
Requires-Dist: spruce-http-common
Requires-Dist: spruce-logging
